cvpysdk/__init__.py
cvpysdk/activate.py
cvpysdk/activitycontrol.py
cvpysdk/agent.py
cvpysdk/alert.py
cvpysdk/array_management.py
cvpysdk/backup_network_pairs.py
cvpysdk/backupset.py
cvpysdk/certificates.py
cvpysdk/client.py
cvpysdk/clientgroup.py
cvpysdk/commcell.py
cvpysdk/commcell_migration.py
cvpysdk/constants.py
cvpysdk/content_analyzer.py
cvpysdk/credential_manager.py
cvpysdk/cvpysdk.py
cvpysdk/deduplication_engines.py
cvpysdk/dev_test_group.py
cvpysdk/disasterrecovery.py
cvpysdk/domains.py
cvpysdk/download_center.py
cvpysdk/eventviewer.py
cvpysdk/exception.py
cvpysdk/globalfilter.py
cvpysdk/hac_clusters.py
cvpysdk/identity_management.py
cvpysdk/index_pools.py
cvpysdk/index_server.py
cvpysdk/instance.py
cvpysdk/internetoptions.py
cvpysdk/job.py
cvpysdk/key_management_server.py
cvpysdk/license.py
cvpysdk/metallic.py
cvpysdk/metricsreport.py
cvpysdk/monitoring.py
cvpysdk/name_change.py
cvpysdk/network.py
cvpysdk/network_throttle.py
cvpysdk/network_topology.py
cvpysdk/operation_window.py
cvpysdk/organization.py
cvpysdk/plan.py
cvpysdk/policy.py
cvpysdk/recovery_targets.py
cvpysdk/regions.py
cvpysdk/resource_pool.py
cvpysdk/schedules.py
cvpysdk/services.py
cvpysdk/storage.py
cvpysdk/storage_pool.py
cvpysdk/subclient.py
cvpysdk/system.py
cvpysdk/tags.py
cvpysdk/virtualmachinepolicies.py
cvpysdk/workflow.py
cvpysdk/activateapps/__init__.py
cvpysdk/activateapps/compliance_utils.py
cvpysdk/activateapps/constants.py
cvpysdk/activateapps/ediscovery_utils.py
cvpysdk/activateapps/entity_manager.py
cvpysdk/activateapps/file_storage_optimization.py
cvpysdk/activateapps/inventory_manager.py
cvpysdk/activateapps/request_manager.py
cvpysdk/activateapps/sensitive_data_governance.py
cvpysdk/agents/__init__.py
cvpysdk/agents/exchange_database_agent.py
cvpysdk/backupsets/__init__.py
cvpysdk/backupsets/aadbackupset.py
cvpysdk/backupsets/adbackupset.py
cvpysdk/backupsets/cabackupset.py
cvpysdk/backupsets/db2backupset.py
cvpysdk/backupsets/fsbackupset.py
cvpysdk-11.40.dist-info/licenses/LICENSE.txt
cvpysdk-11.40.dist-info/WHEEL
cvpysdk-11.40.dist-info/METADATA
cvpysdk-11.40.dist-info/RECORD
