Metadata-Version: 2.4
Name: cvpysdk
Version: 11.40
Summary: Commvault SDK for Python
Keywords: commvault,python,sdk,cv,simpana,commcell,cvlt,webconsole
Author-email: "Commvault Systems Inc." <Dev-PythonSDK@commvault.com>
Requires-Python: >=3.6
Classifier: Development Status :: 5 - Production/Stable
Classifier: License :: OSI Approved :: Apache Software License
License-File: LICENSE.txt
Requires-Dist: requests
Requires-Dist: xmltodict
Project-URL: Bug Tracker, https://github.com/Commvault/cvpysdk/issues
Project-URL: Documentation, https://commvault.github.io/cvpysdk/
Project-URL: Home, https://github.com/Commvault/cvpysdk
Project-URL: Source, https://github.com/Commvault/cvpysdk
